Workbook

Sheet Dashboard
A1: PROYECTOS EN CURSO — DASHBOARD DE PLANIFICACIÓN
A3: ="Cronograma tentativo Ago 2026 – Jul 2027 · "&$A$7&" proyectos activos con término entre Sep-26 y Mar-27 · "&COUNTA('Detalle Proyectos'!C13:C17)&" próximos pasos sin fecha" -> Cronograma tentativo Ago 2026 – Jul 2027 · 8 proyectos activos con término entre Sep-26 y Mar-27 · 5 próximos pasos sin fecha
A5: PROYECTOS ACTIVOS | F5: PROYECTOS POR TRIMESTRE (según mes de término)
A7: =COUNTA('Detalle Proyectos'!C5:C12) -> 8 | F7: T1 Ago–Oct 26 | I7: =COUNTIFS('Detalle Proyectos'!$D$5:$D$12,">="&DATE(2026,8,1),'Detalle Proyectos'!$D$5:$D$12,"<"&DATE(2026,11,1)) -> 6 | J7: =REPT("█",I7) -> ██████
F9: T2 Nov–Ene 27 | I9: =COUNTIFS('Detalle Proyectos'!$D$5:$D$12,">="&DATE(2026,11,1),'Detalle Proyectos'!$D$5:$D$12,"<"&DATE(2027,2,1)) -> 1 | J9: =REPT("█",I9) -> █
A11: =COUNTA('Detalle Proyectos'!C13:C17)&" próximos pasos sin fecha" -> 5 próximos pasos sin fecha | F11: T3 Feb–Abr 27 | I11: =COUNTIFS('Detalle Proyectos'!$D$5:$D$12,">="&DATE(2027,2,1),'Detalle Proyectos'!$D$5:$D$12,"<"&DATE(2027,5,1)) -> 1 | J11: =REPT("█",I11) -> █
F13: T4 May–Jul 27 | I13: =COUNTIFS('Detalle Proyectos'!$D$5:$D$12,">="&DATE(2027,5,1),'Detalle Proyectos'!$D$5:$D$12,"<"&DATE(2027,8,1)) -> 0 | J13: =REPT("█",I13)
A15: CARTA GANTT — PROYECTOS ACTIVOS (AGO-26 A JUL-27)
J16: 2026 | O16: 2027
A17: Proyecto (orden de prioridad) | J17: =DATE(2026,8,1) -> 46235 | K17: =DATE(2026,9,1) -> 46266 | L17: =DATE(2026,10,1) -> 46296 | M17: =DATE(2026,11,1) -> 46327 | N17: =DATE(2026,12,1) -> 46357 | O17: =DATE(2027,1,1) -> 46388 | P17: =DATE(2027,2,1) -> 46419 | Q17: =DATE(2027,3,1) -> 46447 | R17: =DATE(2027,4,1) -> 46478 | S17: =DATE(2027,5,1) -> 46508 | T17: =DATE(2027,6,1) -> 46539 | U17: =DATE(2027,7,1) -> 46569 | V17: Observación
A18: ="#"&'Detalle Proyectos'!$B$5&" · "&'Detalle Proyectos'!$C$5 -> #1 · Cambio de partner | V18: Traspaso de soporte y contratos al nuevo partner SAP · término estimado sep-26
A19: ="#"&'Detalle Proyectos'!$B$6&" · "&'Detalle Proyectos'!$C$6 -> #2 · Integración SimpliRoute | V19: Integración de rutas y despachos con SAP; pruebas y marcha blanca · término estimado oct-26
A20: ="#"&'Detalle Proyectos'!$B$7&" · "&'Detalle Proyectos'!$C$7 -> #3 · Integración Demafront | V20: Integración del servidor Demafront con SAP (pedidos y stock) · término estimado nov-26
A21: ="#"&'Detalle Proyectos'!$B$8&" · "&'Detalle Proyectos'!$C$8 -> #4 · Proyecto de Layout con Partner | V21: Rediseño de layout de procesos junto al partner · término estimado sep-26
A22: ="#"&'Detalle Proyectos'!$B$9&" · "&'Detalle Proyectos'!$C$9 -> #5 · Integración Vcommerce (precios e inventario) | V22: Sincronización de precios e inventario con el ecommerce · término estimado oct-26
A23: ="#"&'Detalle Proyectos'!$B$10&" · "&'Detalle Proyectos'!$C$10 -> #6 · Edificio nuevo — sistema de redes (buscar proveedor) | V23: Cotizar y elegir proveedor de red y cableado del edificio nuevo · término estimado sep-26
A24: ="#"&'Detalle Proyectos'!$B$11&" · "&'Detalle Proyectos'!$C$11 -> #7 · Edificio nuevo — Gantt de próximos pasos | V24: Plan y cronograma de habilitación TI del edificio nuevo · término estimado sep-26
A25: ="#"&'Detalle Proyectos'!$B$12&" · "&'Detalle Proyectos'!$C$12 -> #8 · Google — políticas de mejora, reportería y auditoría de movimientos | V25: Políticas de uso, mejoras y auditoría de movimientos en Google · término estimado mar-27
A27: PRÓXIMOS PASOS — PROYECTOS SIN FECHA DEFINIDA
A28: Proyecto | J28: Observación / próximo paso
A29: ="#"&'Detalle Proyectos'!$B$13&" · "&'Detalle Proyectos'!$C$13 -> #1 · Realizar inventario (evaluar app o desarrollo propio) | J29: Levantamiento de inventario TI y evaluación app de mercado vs desarrollo propio · posible término feb-27
A30: ="#"&'Detalle Proyectos'!$B$14&" · "&'Detalle Proyectos'!$C$14 -> #2 · Integrar SAP y Google | J30: Conectar SAP con Google Workspace (usuarios, archivos y notificaciones) · posible término feb-27
A31: ="#"&'Detalle Proyectos'!$B$15&" · "&'Detalle Proyectos'!$C$15 -> #3 · Proyecto WMS | J31: Evaluar e implementar gestión de bodega (WMS) integrada a SAP · posible término ene-27
A32: ="#"&'Detalle Proyectos'!$B$16&" · "&'Detalle Proyectos'!$C$16 -> #4 · Diagrama de flujo (compra, venta, reposición equipos) | J32: Documentar el flujo de compra, venta y reposición de equipos · posible término dic-27
A33: ="#"&'Detalle Proyectos'!$B$17&" · "&'Detalle Proyectos'!$C$17 -> #5 · Administrar APP — Inventario TI | J33: Puesta en marcha y administración de la app de Inventario TI · posible término dic-27
A35: Nota: fechas tentativas. Las barras van desde ago-26 hasta el mes de término de cada proyecto (hoja 'Detalle Proyectos'). Las observaciones se escriben directamente en este dashboard.

Sheet Detalle Proyectos
A1: CRONOGRAMA TENTATIVO — DE MÁS A MENOS PRIORITARIO
A2: Orden por prioridad · los 8 primeros con mes de término; el resto son próximos pasos sin fecha.
A4: Prioridad | B4: # | C4: Proyecto | D4: Mes de término
A5: 1 | B5: 1 | C5: Cambio de partner | D5: 46266
A6: 2 | B6: 2 | C6: Integración SimpliRoute | D6: 46296
A7: 3 | B7: 3 | C7: Integración Demafront | D7: 46327
A8: 4 | B8: 4 | C8: Proyecto de Layout con Partner | D8: 46266
A9: 5 | B9: 5 | C9: Integración Vcommerce (precios e inventario) | D9: 46296
A10: 6 | B10: 6 | C10: Edificio nuevo — sistema de redes (buscar proveedor) | D10: 46266
A11: 7 | B11: 7 | C11: Edificio nuevo — Gantt de próximos pasos | D11: 46266
A12: 8 | B12: 8 | C12: Google — políticas de mejora, reportería y auditoría de movimientos | D12: 46447
A13: 1 | B13: 1 | C13: Realizar inventario (evaluar app o desarrollo propio) | D13: Sin fecha
A14: 2 | B14: 2 | C14: Integrar SAP y Google | D14: Sin fecha
A15: 3 | B15: 3 | C15: Proyecto WMS | D15: Sin fecha
A16: 4 | B16: 4 | C16: Diagrama de flujo (compra, venta, reposición equipos) | D16: Sin fecha
A17: 5 | B17: 5 | C17: Administrar APP — Inventario TI | D17: Sin fecha

Sheet Tareas Cotidianas
A1: TAREAS COTIDIANAS
A2: Actividades del día a día, funciones adicionales asumidas y tareas esporádicas
A4: # | B4: Tarea | C4: Usuarios promedio | D4: Observaciones
A5: 1 | B5: Revisar integración Ecommerce | C5: 2 | D5: Todos los dias en la mañana resolver 2 a 3 horas en servidor de integraciones
A6: 2 | B6: Realizar consultas / Query Manager | C6: 10 | D6: 2 por semana a veces 3 solicitudes en un mes (consultas que pueden durar o demorar hasta 1 semana de desarrollo, dependiendo de la complejidad)
A7: 3 | B7: Formatear computadores y teléfonos | C7: 3 | D7: 3 computadores al mes en promedio a veces mas o ninguno
A8: 4 | B8: Actualizar lista de precios | C8: 2 | D8: 2 veces al año en promedio
A9: 5 | B9: Actualizar cartera de vendedores en sap y autoventa | C9: 2 | D9: 4 veces al año dependiendo rotacion de vendedor
A10: 6 | B10: Administrar, crear y configurar Google | C10: 40 | D10: Todos los usuarios hacen solictudes promedio 4 veces por semana o 10 veces
A11: 7 | B11: Administrar Auto Venta | C11: 3 | D11: Importaciones diarias, todos los dias en la mañana
A12: 8 | B12: Roles y permisos de licencias SAP | C12: 40 | D12: De los 40 usuarios administro solicitudes y prestamos de licencias (ejemplo: mirsa, Diego, Consultores)
A13: 9 | B13: Configurar VPN → Escritorios remotos | C13: 40 | D13: recurrente 15 solicitudes semanas aproximadamente
A14: 10 | B14: Cierre de Mes (apoyo documentación SAP) | C14: 3 | D14: apoyo al cierre contable Magdalena e Italo
A15: 11 | B15: Cargas Masivas DTW | C15: 4 | D15: Actualizacion cartera, precios, arreglos nc, solcitudes de laboarorio recetas, consultores
A16: 12 | B16: Repprta averías, fallas y actualizaciones del sistema | C16: 40 | D16: Por lo genera aviso a grupo de empresa, o grupo sap (seguimiento y apoyo reestablecer sap, autoventa)
A17: 13 | B17: Responsable Mesa de Ayuda (SAP, Dot Solution, Tecnoera y Autoventa) | C17: 1 | D17: Por lo genera soy el responsble de levantar, y hacer seguimiento a los ticket de estos portales
A20: ACTIVIDADES ESPORÁDICAS
A21: # | B21: Tarea | C21: Usuarios promedio | D21: Observaciones
A22: 1 | B22: Facturación (esporádico) | C22: 1 | D22: Cuando Italo lo requiere
A23: 2 | B23: Notas de crédito (esporádico) | C23: 1 | D23: Cuando son Nc con problemas informatico (por lo general es 1 caso por mes )
A24: 3 | B24: Reemplazos administrativos (ya casi no se realiza) | C24: 1 | D24: Cuando Italo lo requiere
A26: ="Resumen: "&COUNTA(B5:B17)&" tareas cotidianas · "&COUNTA(#REF!)&" actividades adicionales · "&COUNTA(B22:B24)&" esporádicas" -> Resumen: 13 tareas cotidianas · 1 actividades adicionales · 3 esporádicas
